reader_rbv/__init__.py
reader_rbv/book.py
reader_rbv/book_cache.py
reader_rbv/book_section.py
reader_rbv/constants.py
reader_rbv/exception.py
reader_rbv/font.py
reader_rbv/image.py
reader_rbv/page.py
reader_rbv/page_cache.py
reader_rbv/reader.py
reader_rbv/text.py
reader_rbv/utils.py
reader_rbv/version.py
reader_rbv-0.7.1.dist-info/LICENSE
reader_rbv-0.7.1.dist-info/WHEEL
reader_rbv-0.7.1.dist-info/METADATA
reader_rbv-0.7.1.dist-info/RECORD
