Metadata-Version: 2.1
Name: reader-rbv
Version: 0.7.1
Summary: SDK / Client python untuk Ruang Baca Virtual Universitas Terbuka.
License: AGPLv3
Keywords: univterbuka,RBV,reader,flowpaper
Author: hexatester
Author-email: habibrohman@protonmail.com
Requires-Python: >=3.8,<4.0
Classifier: Development Status :: 4 - Beta
Classifier: Intended Audience :: Developers
Classifier: License :: OSI Approved :: GNU Affero General Public License v3
Classifier: License :: Other/Proprietary License
Classifier: Operating System :: OS Independent
Classifier: Programming Language :: Python :: 3
Classifier: Programming Language :: Python :: 3.8
Classifier: Programming Language :: Python :: 3.9
Classifier: Programming Language :: Python :: 3.10
Classifier: Programming Language :: Python :: 3
Classifier: Programming Language :: Python :: 3.8
Classifier: Programming Language :: Python :: 3.9
Classifier: Topic :: Education
Requires-Dist: attrs (>=21.0.0,<23.0.0)
Requires-Dist: beautifulsoup4 (>=4.11.1,<5.0.0)
Requires-Dist: cachetools (>=5.2.0,<6.0.0)
Requires-Dist: requests (>=2.28.0,<3.0.0)
Requires-Dist: ujson (>=5.4.0,<6.0.0)
